datashield_opal/__init__.py
datashield_opal/impl.py
datashield_opal-0.1.0.dist-info/WHEEL
datashield_opal-0.1.0.dist-info/LICENSE.txt
datashield_opal-0.1.0.dist-info/METADATA
datashield_opal-0.1.0.dist-info/RECORD
