Metadata-Version: 2.1
Name: datashield-opal
Version: 0.1.0
Summary: 
Home-page: https://www.obiba.org
License: GPL-v3
Author: Yannick Marcon
Author-email: yannick.marcon@obiba.org
Maintainer: Yannick Marcon
Maintainer-email: yannick.marcon@obiba.org
Requires-Python: >=3.7,<4.0
Classifier: License :: Other/Proprietary License
Classifier: Programming Language :: Python :: 3
Classifier: Programming Language :: Python :: 3.7
Classifier: Programming Language :: Python :: 3.8
Classifier: Programming Language :: Python :: 3.9
Classifier: Programming Language :: Python :: 3.10
Classifier: Programming Language :: Python :: 3.11
Requires-Dist: datashield (>=0.1.0,<0.2.0)
Requires-Dist: obiba_opal (>=5.2.0,<6.0.0)
Project-URL: Documentation, https://datashield.github.io/datashield-opal-python
Project-URL: Repository, https://github.com/datashield/datashield-opal-python
